socketwrench/__init__.py
socketwrench/__main__.py
socketwrench/connection.py
socketwrench/handlers.py
socketwrench/openapi.py
socketwrench/public.py
socketwrench/server.py
socketwrench/settings.py
socketwrench/standardlib_dependencies.py
socketwrench/tags.py
socketwrench/types.py
socketwrench/fake_imports/__init__.py
socketwrench/fake_imports/fake_argparse.py
socketwrench/fake_imports/fake_dataclasses.py
socketwrench/fake_imports/fake_datetime.py
socketwrench/fake_imports/fake_functools.py
socketwrench/fake_imports/fake_inspect.py
socketwrench/fake_imports/fake_json.py
socketwrench/fake_imports/fake_logging.py
socketwrench/fake_imports/fake_pathlib.py
socketwrench/fake_imports/fake_tempfile.py
socketwrench/fake_imports/fake_traceback.py
socketwrench/resources/favicon.ico
socketwrench/resources/swagger.html
socketwrench/resources/playground/panels.js
socketwrench/resources/playground/playground.html
socketwrench/resources/playground/playground.js
socketwrench/samples/__init__.py
socketwrench/samples/file_sample.py
socketwrench/samples/sample.py
socketwrench-2.3.1.dist-info/LICENSE
socketwrench-2.3.1.dist-info/METADATA
socketwrench-2.3.1.dist-info/WHEEL
socketwrench-2.3.1.dist-info/top_level.txt
socketwrench-2.3.1.dist-info/RECORD
