Metadata-Version: 2.1
Name: socketwrench
Version: 2.3.1
Summary: A simple Python library for creating web servers and APIs using sockets, supporting openapi and swagger.
Author-email: Torin Halsted <modularizer@gmail.com>
License: This is free and unencumbered software released into the public domain.
Project-URL: Homepage, https://github.com/modularizer/socketwrench
Classifier: Programming Language :: Python :: 3.12
Classifier: Operating System :: OS Independent
Requires-Python: >=3.10
License-File: LICENSE
